utils_lang/Language.py
utils_lang/TTS.py
utils_lang/Translator.py
utils_lang/__init__.py
utils_lang_nuuuwan-1.0.2.dist-info/LICENSE
utils_lang_nuuuwan-1.0.2.dist-info/METADATA
utils_lang_nuuuwan-1.0.2.dist-info/WHEEL
utils_lang_nuuuwan-1.0.2.dist-info/top_level.txt
utils_lang_nuuuwan-1.0.2.dist-info/RECORD
