Metadata-Version: 2.1
Name: utils_lang-nuuuwan
Version: 1.0.2
Summary: Utilities for Languages
Home-page: https://github.com/nuuuwan/utils_lang
Author: Nuwan I. Senaratna
Author-email: nuuuwan@gmail.com
Project-URL: Bug Tracker, https://github.com/nuuuwan/utils_lang/issues
Classifier: Programming Language :: Python :: 3
Classifier: License :: OSI Approved :: MIT License
Classifier: Operating System :: OS Independent
Requires-Python: >=3.10
License-File: LICENSE
Requires-Dist: utils-base-nuuuwan
Requires-Dist: deep-translator
Requires-Dist: gTTS
